mini_lemmatizer/__init__.py
mini_lemmatizer-0.1.1.dist-info/LICENSE
mini_lemmatizer-0.1.1.dist-info/METADATA
mini_lemmatizer-0.1.1.dist-info/WHEEL
mini_lemmatizer-0.1.1.dist-info/top_level.txt
mini_lemmatizer-0.1.1.dist-info/RECORD
