Metadata-Version: 2.1
Name: mini_lemmatizer
Version: 0.1.1
Summary: A simple, lightweight lemmatization utility built with NLTK.
Home-page: https://github.com/yourusername/mini_lemmatizer
Author: Sania Jain
Author-email: saniiasjain@gmail.com
Classifier: Programming Language :: Python :: 3
Classifier: License :: OSI Approved :: MIT License
Classifier: Operating System :: OS Independent
Requires-Python: >=3.7
License-File: LICENSE
Requires-Dist: nltk>=3.9
